{
    "code": "200",
    "data": [
        {
            "actors": "范冰冰 | 韩庚 | 齐溪 | 沈婷婷 | 沙溢 | 杨迪 | 张博宇 | 赵一维 | 吴莫愁 | 雷恪生 | 李梦 | 吕行",
            "director": "李玉",
            "jdPicAddr": "http://img14.360buyimg.com/movie/jfs/t1030/359/578200917/117169/a2bbed60/553069acNbbb07480.png",
            "like": "388",
            "movieId": "13901",
            "movieName": "万物生长",
            "releaseDate": "2015-04-17 00:00:00",
            "score": "7.5",
            "tmplateType": "2D"
        },
        {
            "actors": "杰森·斯坦森|道恩·强森|范·迪塞尔|保罗·沃克|龙达·鲁西",
            "director": "温子仁",
            "jdPicAddr": "http://img14.360buyimg.com/movie/jfs/t922/200/461024118/78049/d93779da/5525f673N7f0ff50e.jpg",
            "like": "5211",
            "movieId": "13400",
            "movieName": "速度与激情7",
            "releaseDate": "2015-04-12 00:00:00",
            "score": "9.8",
            "tmplateType": "2D"
        },
        {
            "actors": "柯林·菲尔斯|塞缪尔·杰克逊|迈克尔·凯恩",
            "director": "马修·沃恩",
            "jdPicAddr": "http://img14.360buyimg.com/movie/jfs/t580/8/1478985087/200725/2b5ebd1f/54fd0e65Naa72d4f8.jpg",
            "like": "586",
            "movieId": "13263",
            "movieName": "王牌特工：特工学院",
            "releaseDate": "2015-03-27 00:00:00",
            "score": "9.0",
            "tmplateType": "2D"
        },
        {
            "actors": "约翰尼·德普|格温妮斯·帕特洛|保罗·贝坦尼|伊万·麦克格雷格",
            "director": "大卫·凯普",
            "jdPicAddr": "http://pic.maizuo.com/usr/100002151/3e4a533706629b3d149cd0758246b69a.tmp",
            "like": "116",
            "movieId": "13425",
            "movieName": "贵族大盗",
            "releaseDate": "2015-04-17 00:00:00",
            "score": "6.5",
            "tmplateType": "2D"
        },
        {
            "actors": "吴京 / 余男 / 斯科特·阿金斯 / 凯尔·夏皮罗 / 凯文·李 / 塞缪尔·西维尔奇 / 索纳·伊姆贝",
            "director": "吴京",
            "jdPicAddr": "http://img14.360buyimg.com/movie/jfs/t766/172/1320136766/51464/541b8e59/55302e88Nd687a7ae.jpg",
            "like": "1939",
            "movieId": "13421",
            "movieName": "战狼",
            "releaseDate": "2015-04-02 00:00:00",
            "score": "9.6",
            "tmplateType": "3D"
        },
        {
            "actors": "高圆圆|姜武|李晨|郑恺|陈意涵",
            "director": "刘江",
            "jdPicAddr": "http://img14.360buyimg.com/movie/jfs/t934/249/175280538/262099/5ba99a8a/5505fe88Ne35cd4a9.jpg",
            "like": "1253",
            "movieId": "13340",
            "movieName": "咱们结婚吧",
            "releaseDate": "2015-04-02 00:00:00",
            "score": "9.5",
            "tmplateType": "2D"
        },
        {
            "actors": "安泽豪|方力申|王双宝|计春华|焦恩俊",
            "director": "梁杰",
            "jdPicAddr": "http://img14.360buyimg.com/movie/jfs/t706/128/1336609407/12594/48299f3f/55302e88Ne8665ff8.jpg",
            "like": "34",
            "movieId": "14254",
            "movieName": "枪过境",
            "releaseDate": "2015-04-16 00:00:00",
            "score": "0.0",
            "tmplateType": "2D"
        },
        {
            "actors": "宋慧乔|窦骁|邬君梅|姜武|陈乔恩",
            "director": "伊能静",
            "jdPicAddr": "http://img14.360buyimg.com/movie/jfs/t1183/30/573544379/13693/328e4d89/55302e88N2ba4423b.jpg",
            "like": "88",
            "movieId": "13922",
            "movieName": "我是女王",
            "releaseDate": "2015-04-15 00:00:00",
            "score": "4.3",
            "tmplateType": "2D"
        },
        {
            "actors": "康康|李国煌|吴孟达|王彩桦|王予柔",
            "director": "康康",
            "jdPicAddr": "http://img14.360buyimg.com/movie/jfs/t1105/267/304720912/271314/f414ac7c/55147f08Ned1fc503.jpg",
            "like": "41",
            "movieId": "13476",
            "movieName": "十万伙急",
            "releaseDate": "2015-04-17 00:00:00",
            "score": "0.0",
            "tmplateType": "2D"
        }
    ]
}